libneug_grape_lite.so
libneug_libraries.so
neug_py_bind.cpython-38-x86_64-linux-gnu.so
neug/Session.py
neug/VERSION
neug/__init__.py
neug/async_connection.py
neug/connection.py
neug/database.py
neug/query_result.py
neug/version.py
neug/resources/nexg.pb
neug/resources/planner_config.yaml
neug.libs/libarrow-56e141d0.so.1700.0.0
neug.libs/libboost_atomic-631d56ca.so.1.88.0
neug.libs/libboost_context-d6f8bfde.so.1.88.0
neug.libs/libboost_date_time-992ab15a.so.1.88.0
neug.libs/libboost_filesystem-2c17f016.so.1.88.0
neug.libs/libboost_program_options-f5e49a12.so.1.88.0
neug.libs/libboost_regex-7847edac.so.1.88.0
neug.libs/libboost_system-de8f98e1.so.1.88.0
neug.libs/libboost_thread-cc40b5a7.so.1.88.0
neug.libs/libgflags-2f438c32.so.2.2.2
neug.libs/libglog-c0c2893d.so.0.6.0
neug.libs/libgomp-a34b3233.so.1.0.0
neug.libs/libprotobuf-719533dd.so.32.0.9
neug.libs/libprotoc-cbd8b1c5.so.32.0.9
neug.libs/libunwind-d5b5a318.so.8.0.1
neug.libs/libyaml-cpp-5fb08c70.so.0.8.0
neug-0.1.0.dist-info/METADATA
neug-0.1.0.dist-info/WHEEL
neug-0.1.0.dist-info/top_level.txt
neug-0.1.0.dist-info/zip-safe
neug-0.1.0.dist-info/RECORD
