Metadata-Version: 2.4
Name: neug
Version: 0.1.0
Summary: GraphScope NeuG for python
Home-page: https://github.com/graphscope/neug
Author: GraphScope Team
Author-email: GraphScope Team <graphscope@alibaba-inc.com>
Keywords: Graph,Python,Embedded,Graph Database
Requires-Python: >=3.8
Requires-Dist: pybind11>=2.9.2
Requires-Dist: cibuildwheel>=2.0.0
Requires-Dist: packaging>=24.2
Provides-Extra: test
Requires-Dist: pytest>=6.2.5; extra == "test"
Requires-Dist: black>=23.3.0; extra == "test"
Requires-Dist: flake8==4.0.1; extra == "test"
Requires-Dist: isort==5.10.1; extra == "test"
Dynamic: author
Dynamic: home-page
